matterhorn_pytorch/__func__.py
matterhorn_pytorch/__init__.py
matterhorn_pytorch/_ext/__init__.py
matterhorn_pytorch/_ext/cpp.py
matterhorn_pytorch/_ext/cuda.py
matterhorn_pytorch/_ext/functional.py
matterhorn_pytorch/data/__init__.py
matterhorn_pytorch/data/aedat.py
matterhorn_pytorch/data/functional.py
matterhorn_pytorch/data/hdf5.py
matterhorn_pytorch/data/nmnist.py
matterhorn_pytorch/data/skeleton.py
matterhorn_pytorch/data/transforms.py
matterhorn_pytorch/lsm/__init__.py
matterhorn_pytorch/lsm/functional.py
matterhorn_pytorch/lsm/io.py
matterhorn_pytorch/lsm/layer.py
matterhorn_pytorch/model/__init__.py
matterhorn_pytorch/model/sew.py
matterhorn_pytorch/model/ta.py
matterhorn_pytorch/snn/__init__.py
matterhorn_pytorch/snn/container.py
matterhorn_pytorch/snn/decoder.py
matterhorn_pytorch/snn/encoder.py
matterhorn_pytorch/snn/firing.py
matterhorn_pytorch/snn/functional.py
matterhorn_pytorch/snn/layer.py
matterhorn_pytorch/snn/skeleton.py
matterhorn_pytorch/snn/soma.py
matterhorn_pytorch/snn/soma_cpp.py
matterhorn_pytorch/snn/soma_cuda.py
matterhorn_pytorch/snn/soma_functional.py
matterhorn_pytorch/snn/surrogate.py
matterhorn_pytorch/snn/synapse.py
matterhorn_pytorch/tnn/__init__.py
matterhorn_pytorch/tnn/column.py
matterhorn_pytorch/tnn/component.py
matterhorn_pytorch/tnn/functional.py
matterhorn_pytorch/training/__init__.py
matterhorn_pytorch/training/functional.py
matterhorn_pytorch/util/__init__.py
matterhorn_pytorch/util/converter.py
matterhorn_pytorch/util/interpreter.py
matterhorn_pytorch/util/plotter.py
matterhorn_pytorch-1.4.3.dist-info/LICENSE
matterhorn_pytorch-1.4.3.dist-info/METADATA
matterhorn_pytorch-1.4.3.dist-info/WHEEL
matterhorn_pytorch-1.4.3.dist-info/top_level.txt
matterhorn_pytorch-1.4.3.dist-info/RECORD
