Metadata-Version: 2.1
Name: matterhorn_pytorch
Version: 1.4.3
Summary: Matterhorn is a novel general neuromorphic computing framework based on PyTorch.
Home-page: https://github.com/xjtuiair-cag/Matterhorn
Author: CAG, IAIR, XJTU, Xi'an, China
Author-email: ericwang017@stu.xjtu.edu.cn
License: License :: OSI Approved :: MIT License
Classifier: Programming Language :: Python :: 3 :: Only
Classifier: License :: OSI Approved :: MIT License
Classifier: Operating System :: OS Independent
Requires-Python: >=3.7
License-File: LICENSE
Requires-Dist: numpy
Requires-Dist: matplotlib
Requires-Dist: ninja
Requires-Dist: h5py
Requires-Dist: tqdm
Requires-Dist: rich
Requires-Dist: torch
Requires-Dist: torchvision
Requires-Dist: pyecharts
